{
	"id": "3dff0e8f-c57b-47c1-8a12-5e743b68b8dc",
	"name": "group29_env",
	"values": [
		{
			"key": "name",
			"value": "Viktoriia",
			"type": "default",
			"enabled": true
		},
		{
			"key": "age",
			"value": "20",
			"type": "default",
			"enabled": true
		},
		{
			"key": "salary",
			"value": "3000",
			"type": "default",
			"enabled": true
		},
		{
			"key": "weight",
			"value": "50",
			"type": "default",
			"enabled": true
		},
		{
			"key": "url",
			"value": "http://162.55.220.72:5005",
			"type": "default",
			"enabled": true
		}
	],
	"_postman_variable_scope": "environment",
	"_postman_exported_at": "2022-05-10T18:14:39.213Z",
	"_postman_exported_using": "Postman/9.17.2"
}